smart_jit/__init__.py
smart_jit/action.py
smart_jit/smartjit.py
smart_jit/warnings.py
numba_smartjit-0.0.1.dist-info/LICENSE.md
numba_smartjit-0.0.1.dist-info/WHEEL
numba_smartjit-0.0.1.dist-info/METADATA
numba_smartjit-0.0.1.dist-info/RECORD
