Metadata-Version: 2.1
Name: numba-smartjit
Version: 0.0.1
Summary: 
Requires-Python: >=3.7
Classifier: License :: OSI Approved :: MIT License
Classifier: Programming Language :: Python :: 3
Classifier: Programming Language :: Python :: 3.7
Classifier: Programming Language :: Python :: 3.8
Classifier: Programming Language :: Python :: 3.9
Classifier: Programming Language :: Python :: 3.10
Classifier: Programming Language :: Python :: 3.11
Classifier: Operating System :: OS Independent
Classifier: Topic :: Software Development
Requires-Dist: numba
Requires-Dist: flit ; extra == "dev"
Requires-Dist: pytest ; extra == "test"
Project-URL: Home, https://github.com/Quansight/numba-smartjit
Project-URL: Source, https://github.com/Quansight/numba-smartjit
Provides-Extra: dev
Provides-Extra: doc
Provides-Extra: test
